fusion/__init__.py
fusion/__main__.py
fusion/client.py
fusion/config.py
fusion/device.py
fusion/exceptions.py
fusion/index.py
fusion/path.py
fusion/storage.py
fusion/configs/__init__.py
fusion/configs/config.json
fusion/configs/default.json
fusion/helpers/__init__.py
fusion/helpers/completion.py
fusion/helpers/constants.py
fusion/helpers/deleteListing.py
fusion/helpers/file.py
fusion/helpers/fileListing.py
fusion/helpers/interface.py
fusion/helpers/logger.py
fusion/helpers/progress.py
fusion/helpers/stat.py
fusion/helpers/utils.py
fusion/ui/__init__.py
fusion/ui/container.py
fusion/ui/keyboard_window.py
fusion/ui/message.py
fusion/ui/progress_bar.py
fusion/ui/prompt_list.py
tests/__init__.py
tests/conftest.py
tests/test_pull.py
tests/test_push.py
fusion_sync-0.4.0.dist-info/LICENSE
fusion_sync-0.4.0.dist-info/METADATA
fusion_sync-0.4.0.dist-info/WHEEL
fusion_sync-0.4.0.dist-info/entry_points.txt
fusion_sync-0.4.0.dist-info/top_level.txt
fusion_sync-0.4.0.dist-info/RECORD
