Metadata-Version: 2.1
Name: fusion-sync
Version: 0.4.0
Summary: Keep your files in sync
Author: Mohammad Mallaee
License: GPLv3
License-File: LICENSE
Requires-Dist: pytermgui
Requires-Dist: argcomplete
